pyplatform/common/__init__.py
pyplatform/common/local_files.py
pyplatform/common/pivotal_cloud.py
pyplatform/common/udf.py
pyplatform/common/utils.py
pyplatform_common-2020.12.1.dist-info/METADATA
pyplatform_common-2020.12.1.dist-info/WHEEL
pyplatform_common-2020.12.1.dist-info/top_level.txt
pyplatform_common-2020.12.1.dist-info/RECORD
