Metadata-Version: 2.1
Name: pyplatform-common
Version: 2020.12.1
Summary: Pyplatform-common package provides utility, file management and authentication functions for interacting with APIs and compute services.
Home-page: https://github.com/mhadi813/pyplatform
Author: Muhammad Hadi
Author-email: mhadi813@gmail.com
License: BSD
Keywords: google API pivotal cloud functions
Platform: UNKNOWN
Classifier: Development Status :: 4 - Beta
Classifier: Intended Audience :: Developers
Classifier: Topic :: Office/Business
Classifier: License :: OSI Approved :: BSD License
Classifier: Programming Language :: Python :: 3.6
Classifier: Programming Language :: Python :: 3.7
Classifier: Programming Language :: Python :: 3.8
Requires-Dist: pandas (==1.1.2)
Requires-Dist: oauth2client (==4.1.3)
Requires-Dist: pytz (==2019.3)
Requires-Dist: requests (==2.23.0)
Requires-Dist: requests-ntlm (==1.1.0)
Requires-Dist: PyJWT (==1.7.1)
Requires-Dist: retrying (==1.3.3)
Requires-Dist: bs4 (==0.0.1)
Requires-Dist: lxml (==4.4.2)
Requires-Dist: fsspec (==0.8.0)
Requires-Dist: gcsfs (==0.7.0)
